dman/__init__.py
dman/cli.py
dman/config.py
dman/numeric.py
dman/plotting.py
dman/tui.py
dman/core/__init__.py
dman/core/errors.py
dman/core/log.py
dman/core/path.py
dman/core/serializables.py
dman/core/storables.py
dman/model/__init__.py
dman/model/modelclasses.py
dman/model/record.py
dman/model/repository.py
dman/utils/__init__.py
dman/utils/regex.py
dman/utils/sjson.py
dman/utils/smartdataclasses.py
dman/utils/user.py
dman-1.0.1.dist-info/entry_points.txt
dman-1.0.1.dist-info/LICENSE
dman-1.0.1.dist-info/WHEEL
dman-1.0.1.dist-info/METADATA
dman-1.0.1.dist-info/RECORD
